[
  {
    "platform": "Reddit",
    "name": "Reddit: games",
    "url": "https://www.reddit.com/search/?q=games+community",
    "description": "Search results for community"
  },
  {
    "platform": "Reddit",
    "name": "Reddit: action",
    "url": "https://www.reddit.com/search/?q=action+community",
    "description": "Search results for community"
  },
  {
    "platform": "Reddit",
    "name": "Reddit: ghost of tsushima",
    "url": "https://www.reddit.com/search/?q=ghost+of+tsushima+community",
    "description": "Search results for community"
  }
]